pytest_report_extras/__init__.py
pytest_report_extras/attachment.py
pytest_report_extras/decorators.py
pytest_report_extras/extras.py
pytest_report_extras/link.py
pytest_report_extras/mime.py
pytest_report_extras/plugin.py
pytest_report_extras/status.py
pytest_report_extras/utils.py
pytest_report_extras/resources/error.png
pytest_report_extras/resources/style.css
pytest_report_extras-1.3.8.dist-info/entry_points.txt
pytest_report_extras-1.3.8.dist-info/licenses/LICENSE
pytest_report_extras-1.3.8.dist-info/WHEEL
pytest_report_extras-1.3.8.dist-info/METADATA
pytest_report_extras-1.3.8.dist-info/RECORD
