Metadata-Version: 2.4
Name: pytest-report-extras
Version: 1.3.8
Summary: Pytest plugin to enhance pytest-html and allure reports by adding comments, screenshots, webpage sources and attachments.
Keywords: pytest,selenium,playwright,webtest,webtesting
Author-email: Harmin Parra Rueda <harmin.rueda@gmail.com>
Requires-Python: >=3.11
Classifier: Framework :: Pytest
Classifier: License :: OSI Approved :: MIT License
Classifier: Topic :: Software Development :: Quality Assurance
Classifier: Topic :: Software Development :: Testing
License-File: LICENSE
Requires-Dist: pytest >= 8.4.0
Requires-Dist: pyyaml >= 6.0.2
Requires-Dist: beautifulsoup4 >= 4.13.0
